aplicacion_ventas/__init__.py
aplicacion_ventas/descuentos.py
aplicacion_ventas/excepciones.py
aplicacion_ventas/gestor_ventas.py
aplicacion_ventas/impuestos.py
aplicacion_ventas/precios.py
aplicacon_ventas_aruiz-0.1.0.dist-info/licenses/LICENSE
test/__init__.py
test/test_aplicacion_ventas.py
aplicacon_ventas_aruiz-0.1.0.dist-info/METADATA
aplicacon_ventas_aruiz-0.1.0.dist-info/WHEEL
aplicacon_ventas_aruiz-0.1.0.dist-info/top_level.txt
aplicacon_ventas_aruiz-0.1.0.dist-info/RECORD
