Metadata-Version: 2.4
Name: aplicacon_ventas_aruiz
Version: 0.1.0
Summary: Paquete para gestionar, ventas, precios, impuestos y descuentos
Home-page: http://github.com/curso_python_camara/gestor/apliacion_ventas
Author: Liliana Mora
Author-email: liliana@gmail.com
Classifier: Development Status :: 3 - Alpha
Classifier: License :: OSI Approved :: MIT License
Classifier: Operating System :: OS Independent
Requires-Python: >=3.7
License-File: LICENSE
Dynamic: author
Dynamic: author-email
Dynamic: classifier
Dynamic: description
Dynamic: description-content-type
Dynamic: home-page
Dynamic: license-file
Dynamic: requires-python
Dynamic: summary
